glag.py
glag-0.3.0.dist-info/METADATA
glag-0.3.0.dist-info/WHEEL
glag-0.3.0.dist-info/RECORD
