Metadata-Version: 2.1
Name: glag
Version: 0.3.0
Summary: glag
Author: Keith Griffon
Requires-Python: >=3.11,<4.0
Classifier: Programming Language :: Python :: 3
Classifier: Programming Language :: Python :: 3.11
